{"\u00c5l":{"Familie":"\u00c5lefamilien","Art":"\u00c5l","Latin":"Anguilla anguilla","Lengde":150.0,"Vekt":12700.0,"Norgesrekord":3850.0,"Link":"https:\/\/snl.no\/%C3%A5l","Link_rekord":"https:\/\/www.klikk.no\/produkthjemmesider\/villmarksliv\/al-anguilla-anguilla-3208991","Minimum_dyp":null,"Maximum_dyp":null},"Laks":{"Familie":"Laksefamilien","Art":"Laks","Latin":"Salmo salar","Lengde":160.0,"Vekt":50000.0,"Norgesrekord":32500.0,"Link":"https:\/\/no.wikipedia.org\/wiki\/Laks","Link_rekord":"https:\/\/www.klikk.no\/produkthjemmesider\/villmarksliv\/laks-salmo-salar-3207962","Minimum_dyp":null,"Maximum_dyp":null},"Pukkellaks":{"Familie":"Laksefamilien","Art":"Pukkellaks","Latin":"Oncorhynchus gorbuscha","Lengde":80.0,"Vekt":7000.0,"Norgesrekord":3973.0,"Link":"https:\/\/snl.no\/pukkellaks","Link_rekord":"https:\/\/www.klikk.no\/produkthjemmesider\/villmarksliv\/pukkellaks-oncorhynchus-gorbuscha-3208919","Minimum_dyp":null,"Maximum_dyp":null},"Ketalaks":{"Familie":"Laksefamilien","Art":"Ketalaks","Latin":"Oncorhynchus keta","Lengde":112.0,"Vekt":19000.0,"Norgesrekord":5100.0,"Link":"https:\/\/snl.no\/ketalaks","Link_rekord":"https:\/\/www.klikk.no\/produkthjemmesider\/villmarksliv\/ketalaks-oncorhynchus-keta-3207940?token=1138835117","Minimum_dyp":null,"Maximum_dyp":null},"\u00d8rret":{"Familie":"Laksefamilien","Art":"\u00d8rret","Latin":"Salmo trutta","Lengde":140.0,"Vekt":20000.0,"Norgesrekord":15300.0,"Link":"https:\/\/snl.no\/%C3%B8rret","Link_rekord":"https:\/\/www.klikk.no\/produkthjemmesider\/villmarksliv\/orret-salmo-trutta-3204923","Minimum_dyp":null,"Maximum_dyp":null},"Regnbue\u00f8rret":{"Familie":"Laksefamilien","Art":"Regnbue\u00f8rret","Latin":"Oncorhynchus mykiss","Lengde":90.0,"Vekt":12000.0,"Norgesrekord":11495.0,"Link":"https:\/\/no.wikipedia.org\/wiki\/Regnbue%C3%B8rret","Link_rekord":"https:\/\/www.klikk.no\/produkthjemmesider\/villmarksliv\/regnbueorret-oncorhynchus-mykiss-3208929","Minimum_dyp":null,"Maximum_dyp":null},"R\u00f8ye":{"Familie":"Laksefamilien","Art":"R\u00f8ye","Latin":"Salvelinus alpinus","Lengde":null,"Vekt":12000.0,"Norgesrekord":8285.0,"Link":"https:\/\/no.wikipedia.org\/wiki\/R%C3%B8ye","Link_rekord":"https:\/\/www.klikk.no\/produkthjemmesider\/villmarksliv\/roye-salvelinus-alpinus-3208939","Minimum_dyp":null,"Maximum_dyp":null},"Bekker\u00f8ye":{"Familie":"Laksefamilien","Art":"Bekker\u00f8ye","Latin":"Salvelinus fontinalis","Lengde":86.0,"Vekt":4000.0,"Norgesrekord":2268.0,"Link":"https:\/\/no.wikipedia.org\/wiki\/Bekker%C3%B8ye","Link_rekord":"https:\/\/www.klikk.no\/produkthjemmesider\/villmarksliv\/bekkeroye-salvelinus-fluviatilis-3207562","Minimum_dyp":null,"Maximum_dyp":null},"Canadar\u00f8ye":{"Familie":"Laksefamilien","Art":"Canadar\u00f8ye","Latin":"Salvelinus namaycush","Lengde":100.0,"Vekt":15000.0,"Norgesrekord":10200.0,"Link":"https:\/\/snl.no\/kanadar%C3%B8ye","Link_rekord":"https:\/\/www.hooked.no\/artikler\/vilhelm-knuste-norgesrekorden-pa-umulig-fisk","Minimum_dyp":null,"Maximum_dyp":null},"Sik":{"Familie":"Laksefamilien","Art":"Sik","Latin":"Coregonus lavaretus","Lengde":70.0,"Vekt":10000.0,"Norgesrekord":4150.0,"Link":"https:\/\/no.wikipedia.org\/wiki\/Sik","Link_rekord":"https:\/\/www.klikk.no\/produkthjemmesider\/villmarksliv\/sik-coregonus-lavaretus-3208949","Minimum_dyp":null,"Maximum_dyp":null},"Lagesild":{"Familie":"Laksefamilien","Art":"Lagesild","Latin":"Coregonus albula","Lengde":35.0,"Vekt":300.0,"Norgesrekord":251.0,"Link":"https:\/\/snl.no\/lagesild","Link_rekord":null,"Minimum_dyp":null,"Maximum_dyp":null},"Harr":{"Familie":"Laksefamilien","Art":"Harr","Latin":"Thymallus thymallus","Lengde":60.0,"Vekt":3500.0,"Norgesrekord":1900.0,"Link":"https:\/\/snl.no\/harr","Link_rekord":"https:\/\/www.klikk.no\/produkthjemmesider\/villmarksliv\/harr-thymallus-thymallus-3207880","Minimum_dyp":null,"Maximum_dyp":null},"Kr\u00f8kle":{"Familie":"Loddefamilien","Art":"Kr\u00f8kle","Latin":"Osmerus eperlanus","Lengde":34.0,"Vekt":100.0,"Norgesrekord":64.0,"Link":"https:\/\/snl.no\/kr%C3%B8kle","Link_rekord":"https:\/\/www.klikk.no\/produkthjemmesider\/villmarksliv\/krokle-osmerus-eperlanus-3208884","Minimum_dyp":null,"Maximum_dyp":null},"Gjedde":{"Familie":"Gjeddefamilien","Art":"Gjedde","Latin":"Esox lucius","Lengde":140.0,"Vekt":30000.0,"Norgesrekord":19540.0,"Link":"https:\/\/no.wikipedia.org\/wiki\/Gjedde","Link_rekord":"https:\/\/www.h-a.no\/helg\/fisk\/norges-storste-gjedde-tatt-paa-stavsjo","Minimum_dyp":null,"Maximum_dyp":null},"Dvergmalle":{"Familie":"Mallefamilien","Art":"Dvergmalle","Latin":"Ameiurus nebulosus","Lengde":48.0,"Vekt":1000.0,"Norgesrekord":604.0,"Link":"https:\/\/no.wikipedia.org\/wiki\/Dvergmalle","Link_rekord":null,"Minimum_dyp":null,"Maximum_dyp":null},"Mort":{"Familie":"Karpefamilien","Art":"Mort","Latin":"Rutilus rutilus","Lengde":46.0,"Vekt":1300.0,"Norgesrekord":1160.0,"Link":"https:\/\/no.wikipedia.org\/wiki\/Mort","Link_rekord":"https:\/\/www.klikk.no\/produkthjemmesider\/villmarksliv\/mort-rutilus-rutilus-3208910","Minimum_dyp":null,"Maximum_dyp":null},"Gullbust":{"Familie":"Karpefamilien","Art":"Gullbust","Latin":"Leuciscus leuciscus","Lengde":40.0,"Vekt":1000.0,"Norgesrekord":604.0,"Link":"https:\/\/no.wikipedia.org\/wiki\/Gullbust","Link_rekord":"https:\/\/www.klikk.no\/produkthjemmesider\/villmarksliv\/gullbust-leuciscus-leuciscus-3207890","Minimum_dyp":null,"Maximum_dyp":null},"Stam":{"Familie":"Karpefamilien","Art":"Stam","Latin":"Leuciscus cephalus","Lengde":80.0,"Vekt":8000.0,"Norgesrekord":3430.0,"Link":"https:\/\/no.wikipedia.org\/wiki\/Stam","Link_rekord":"https:\/\/www.klikk.no\/produkthjemmesider\/villmarksliv\/stam-squalius-cephalus-3208975","Minimum_dyp":null,"Maximum_dyp":null},"Vederbuk":{"Familie":"Karpefamilien","Art":"Vederbuk","Latin":"Leuciscus idus","Lengde":60.0,"Vekt":4000.0,"Norgesrekord":3940.0,"Link":"https:\/\/no.wikipedia.org\/wiki\/Vederbuk","Link_rekord":"https:\/\/www.hooked.no\/artikler\/skandinavias-storste-vederbuk","Minimum_dyp":null,"Maximum_dyp":null},"\u00d8rekyt":{"Familie":"Karpefamilien","Art":"\u00d8rekyt","Latin":"Phoxinus phoxinus","Lengde":15.0,"Vekt":50.0,"Norgesrekord":40.0,"Link":"https:\/\/no.wikipedia.org\/wiki\/%C3%98rekyte","Link_rekord":" ","Minimum_dyp":null,"Maximum_dyp":null},"S\u00f8rv":{"Familie":"Karpefamilien","Art":"S\u00f8rv","Latin":"Scardinius erythrophthalmus","Lengde":45.0,"Vekt":2000.0,"Norgesrekord":1460.0,"Link":"https:\/\/no.wikipedia.org\/wiki\/S%C3%B8rv","Link_rekord":"https:\/\/www.klikk.no\/produkthjemmesider\/villmarksliv\/sorv-scardinius-erythrophthalmus-2883360","Minimum_dyp":null,"Maximum_dyp":null},"Asp":{"Familie":"Karpefamilien","Art":"Asp","Latin":"Aspius aspius","Lengde":90.0,"Vekt":6000.0,"Norgesrekord":5340.0,"Link":"https:\/\/no.wikipedia.org\/wiki\/Asp_(fisk)","Link_rekord":"https:\/\/www.klikk.no\/produkthjemmesider\/villmarksliv\/asp-aspius-aspius-3207592","Minimum_dyp":null,"Maximum_dyp":null},"Regnlaue":{"Familie":"Karpefamilien","Art":"Regnlaue","Latin":"Leucaspius delineatus","Lengde":12.0,"Vekt":3.0,"Norgesrekord":2.6,"Link":"https:\/\/no.wikipedia.org\/wiki\/Regnlaue","Link_rekord":null,"Minimum_dyp":null,"Maximum_dyp":null},"Suter":{"Familie":"Karpefamilien","Art":"Suter","Latin":"Tinca tinca","Lengde":60.0,"Vekt":4000.0,"Norgesrekord":3960.0,"Link":"https:\/\/no.wikipedia.org\/wiki\/Suter","Link_rekord":"https:\/\/www.klikk.no\/produkthjemmesider\/villmarksliv\/suter-tinca-tinca-3242802","Minimum_dyp":null,"Maximum_dyp":null},"Laue":{"Familie":"Karpefamilien","Art":"Laue","Latin":"Alburnus alburnus","Lengde":20.0,"Vekt":100.0,"Norgesrekord":100.0,"Link":"https:\/\/no.wikipedia.org\/wiki\/Laue","Link_rekord":"https:\/\/www.klikk.no\/produkthjemmesider\/villmarksliv\/laue-alburnus-alburnus-3208900","Minimum_dyp":null,"Maximum_dyp":null},"Karuss":{"Familie":"Karpefamilien","Art":"Karuss","Latin":"Carassius carassius","Lengde":45.0,"Vekt":3500.0,"Norgesrekord":2784.0,"Link":"https:\/\/no.wikipedia.org\/wiki\/Karuss","Link_rekord":"https:\/\/www.klikk.no\/produkthjemmesider\/villmarksliv\/karuss-carassius-carassius-3207930?token=1099372219","Minimum_dyp":null,"Maximum_dyp":null},"Gullfisk":{"Familie":"Karpefamilien","Art":"Gullfisk","Latin":"Carassius auratus","Lengde":40.0,"Vekt":1500.0,"Norgesrekord":1390.0,"Link":"https:\/\/no.wikipedia.org\/wiki\/Gullfisk","Link_rekord":"https:\/\/www.klikk.no\/produkthjemmesider\/villmarksliv\/gullfisk-carassius-auratus-3207900","Minimum_dyp":null,"Maximum_dyp":null},"Brasme":{"Familie":"Karpefamilien","Art":"Brasme","Latin":"Abramis brama","Lengde":70.0,"Vekt":7000.0,"Norgesrekord":5526.0,"Link":"https:\/\/no.wikipedia.org\/wiki\/Brasme","Link_rekord":"https:\/\/www.klikk.no\/produkthjemmesider\/villmarksliv\/brasme-abramis-brama-3207572","Minimum_dyp":null,"Maximum_dyp":null},"Flire":{"Familie":"Karpefamilien","Art":"Flire","Latin":"Blicca bjoerkna","Lengde":35.0,"Vekt":2000.0,"Norgesrekord":1160.0,"Link":"https:\/\/no.wikipedia.org\/wiki\/Flire","Link_rekord":null,"Minimum_dyp":null,"Maximum_dyp":null},"Karpe":{"Familie":"Karpefamilien","Art":"Karpe","Latin":"Cyprinus carpio","Lengde":100.0,"Vekt":20000.0,"Norgesrekord":13600.0,"Link":"https:\/\/snl.no\/karpe","Link_rekord":null,"Minimum_dyp":null,"Maximum_dyp":null},"Sandkryper":{"Familie":"Karpefamilien","Art":"Sandkryper","Latin":"Gobio gobio","Lengde":21.0,"Vekt":null,"Norgesrekord":null,"Link":"https:\/\/no.wikipedia.org\/wiki\/Sandkryper","Link_rekord":null,"Minimum_dyp":null,"Maximum_dyp":null},"Lake":{"Familie":"Torskefamilien","Art":"Lake","Latin":"Lota lota","Lengde":115.0,"Vekt":8000.0,"Norgesrekord":7000.0,"Link":"https:\/\/snl.no\/lake_-_fiskeart","Link_rekord":"https:\/\/www.klikk.no\/produkthjemmesider\/villmarksliv\/lake-lota-lota-3207972","Minimum_dyp":null,"Maximum_dyp":null},"Trepigget stingsild":{"Familie":"Stingsildfamilien","Art":"Trepigget stingsild","Latin":"Gasterosteus aculeatus","Lengde":11.0,"Vekt":15.0,"Norgesrekord":11.0,"Link":"https:\/\/snl.no\/trepigget_stingsild","Link_rekord":null,"Minimum_dyp":null,"Maximum_dyp":null},"Nipigget stingsild":{"Familie":"Stingsildfamilien","Art":"Nipigget stingsild","Latin":"Pungitius pungitius","Lengde":7.0,"Vekt":3.0,"Norgesrekord":3.39,"Link":"https:\/\/no.wikipedia.org\/wiki\/Nipigget_stingsild","Link_rekord":"https:\/\/www.klikk.no\/produkthjemmesider\/villmarksliv\/stingsild-trepigget-gasterosteus-aculeatus-3222813","Minimum_dyp":null,"Maximum_dyp":null},"Steinsmett":{"Familie":"Ulkefamilien","Art":"Steinsmett","Latin":"Cottus poecilopus","Lengde":12.0,"Vekt":25.0,"Norgesrekord":20.0,"Link":"https:\/\/no.wikipedia.org\/wiki\/Steinsmett","Link_rekord":"https:\/\/www.klikk.no\/produkthjemmesider\/villmarksliv\/steinsmett-cottus-poecilopus-3295892","Minimum_dyp":null,"Maximum_dyp":null},"Hvitfinnet steinulke":{"Familie":"Ulkefamilien","Art":"Hvitfinnet steinulke","Latin":"Cottus gobio","Lengde":17.0,"Vekt":15.0,"Norgesrekord":8.0,"Link":"https:\/\/snl.no\/hvitfinnet_steinulke","Link_rekord":null,"Minimum_dyp":null,"Maximum_dyp":null},"Hornulke":{"Familie":"Ulkefamilien","Art":"Hornulke","Latin":"Myoxocephalus quadricornis","Lengde":20.0,"Vekt":null,"Norgesrekord":null,"Link":"https:\/\/no.wikipedia.org\/wiki\/Hornulke","Link_rekord":null,"Minimum_dyp":null,"Maximum_dyp":null},"Abbor":{"Familie":"Piggfinnefisker \/ Abborfamilien","Art":"Abbor","Latin":"Perca fluviatilis","Lengde":60.0,"Vekt":4000.0,"Norgesrekord":3170.0,"Link":"https:\/\/no.wikipedia.org\/wiki\/Abbor","Link_rekord":"https:\/\/www.klikk.no\/produkthjemmesider\/villmarksliv\/abbor-perca-fluviatilis-3207612","Minimum_dyp":null,"Maximum_dyp":null},"Hork":{"Familie":"Piggfinnefisker \/ Abborfamilien","Art":"Hork","Latin":"Gymnocephalus cernuus","Lengde":22.0,"Vekt":100.0,"Norgesrekord":101.0,"Link":"https:\/\/no.wikipedia.org\/wiki\/Hork","Link_rekord":"https:\/\/www.klikk.no\/produkthjemmesider\/villmarksliv\/hork-gymnocephalus-cernuus-3207920","Minimum_dyp":null,"Maximum_dyp":null},"Gj\u00f8rs":{"Familie":"Piggfinnefisker \/ Abborfamilien","Art":"Gj\u00f8rs","Latin":"Sander lucioperca","Lengde":130.0,"Vekt":18000.0,"Norgesrekord":11660.0,"Link":"https:\/\/no.wikipedia.org\/wiki\/Gj%C3%B8rs","Link_rekord":"https:\/\/www.klikk.no\/produkthjemmesider\/villmarksliv\/gjors-sander-lucioperca-2883370?token=1755319512","Minimum_dyp":null,"Maximum_dyp":null},"R\u00f8dgjellet solabbor":{"Familie":"Laksabborfamilien","Art":"R\u00f8dgjellet solabbor","Latin":"Lepomis gibbosus","Lengde":25.0,"Vekt":150.0,"Norgesrekord":81.16,"Link":"https:\/\/no.wikipedia.org\/wiki\/R%C3%B8dgjellet_solabbor","Link_rekord":null,"Minimum_dyp":null,"Maximum_dyp":null},"Torsk":{"Familie":"Torskefamilien","Art":"Torsk","Latin":"Gadus morhua","Lengde":200.0,"Vekt":60000.0,"Norgesrekord":41720.0,"Link":"https:\/\/no.wikipedia.org\/wiki\/Torsk","Link_rekord":"https:\/\/www.klikk.no\/produkthjemmesider\/villmarksliv\/torsk-gadus-morhua-2936303","Minimum_dyp":0.0,"Maximum_dyp":600.0},"Sei":{"Familie":"Torskefamilien","Art":"Sei","Latin":"Pollachius virens","Lengde":130.0,"Vekt":32000.0,"Norgesrekord":22700.0,"Link":"https:\/\/snl.no\/sei","Link_rekord":"https:\/\/www.klikk.no\/produkthjemmesider\/villmarksliv\/sei-pollachius-virens-3221921","Minimum_dyp":0.0,"Maximum_dyp":200.0},"Lyr":{"Familie":"Torskefamilien","Art":"Lyr","Latin":"Pollachius pollachius","Lengde":130.0,"Vekt":18000.0,"Norgesrekord":13800.0,"Link":"https:\/\/no.wikipedia.org\/wiki\/Lyr","Link_rekord":null,"Minimum_dyp":0.0,"Maximum_dyp":200.0},"Hyse":{"Familie":"Torskefamilien","Art":"Hyse","Latin":"Melanogrammus aeglefinus","Lengde":100.0,"Vekt":12000.0,"Norgesrekord":9250.0,"Link":"https:\/\/no.wikipedia.org\/wiki\/Hyse","Link_rekord":"https:\/\/www.klikk.no\/produkthjemmesider\/villmarksliv\/hyse-melanogrammus-aeglefinus-2899627","Minimum_dyp":10.0,"Maximum_dyp":450.0},"Skjeggtorsk":{"Familie":"Torskefamilien","Art":"Skjeggtorsk","Latin":"Trisopterus luscus","Lengde":45.0,"Vekt":3000.0,"Norgesrekord":1435.0,"Link":"https:\/\/no.wikipedia.org\/wiki\/Skjeggtorsk","Link_rekord":"https:\/\/www.klikk.no\/produkthjemmesider\/villmarksliv\/skjeggtorsk-trisopterus-luscus-3221998","Minimum_dyp":10.0,"Maximum_dyp":100.0},"S\u00f8lvtorsk":{"Familie":"Torskefamilien","Art":"S\u00f8lvtorsk","Latin":"Gadiculus argenteus","Lengde":15.0,"Vekt":null,"Norgesrekord":55.0,"Link":"https:\/\/snl.no\/s%C3%B8lvtorsk","Link_rekord":"https:\/\/www.klikk.no\/produkthjemmesider\/villmarksliv\/solvtorsk-gadiculus-argenteus-3222868","Minimum_dyp":100.0,"Maximum_dyp":1000.0},"Polartorsk":{"Familie":"Torskefamilien","Art":"Polartorsk","Latin":"Boreogadus saida","Lengde":40.0,"Vekt":null,"Norgesrekord":37.0,"Link":"https:\/\/no.wikipedia.org\/wiki\/Polartorsk","Link_rekord":"https:\/\/www.klikk.no\/produkthjemmesider\/villmarksliv\/polartorsk-boreogadus-saida-3221541","Minimum_dyp":15.0,"Maximum_dyp":80.0},"Hvitting":{"Familie":"Torskefamilien","Art":"Hvitting","Latin":"Merlangius merlangus","Lengde":70.0,"Vekt":3000.0,"Norgesrekord":3115.0,"Link":"https:\/\/no.wikipedia.org\/wiki\/Hvitting","Link_rekord":"https:\/\/www.klikk.no\/produkthjemmesider\/villmarksliv\/hvitting-merlangius-merlangus-3211662","Minimum_dyp":10.0,"Maximum_dyp":200.0},"Kolmule":{"Familie":"Torskefamilien","Art":"Kolmule","Latin":"Micromesistius poutassou","Lengde":80.0,"Vekt":1000.0,"Norgesrekord":932.0,"Link":"https:\/\/no.wikipedia.org\/wiki\/Kolmule","Link_rekord":"https:\/\/www.klikk.no\/produkthjemmesider\/villmarksliv\/kolmule-micromesistius-poutassou-3229484","Minimum_dyp":0.0,"Maximum_dyp":700.0},"Berlev\u00e5gfisk":{"Familie":"Torskefamilien","Art":"Berlev\u00e5gfisk","Latin":"Theragra finnmarchica","Lengde":70.0,"Vekt":null,"Norgesrekord":null,"Link":"https:\/\/no.wikipedia.org\/wiki\/Berlev%C3%A5gfisk","Link_rekord":null,"Minimum_dyp":null,"Maximum_dyp":null},"Sypike":{"Familie":"Torskefamilien","Art":"Sypike","Latin":"Trisopterus minutus","Lengde":40.0,"Vekt":null,"Norgesrekord":388.0,"Link":"https:\/\/no.wikipedia.org\/wiki\/Sypike","Link_rekord":"https:\/\/www.klikk.no\/produkthjemmesider\/villmarksliv\/sypike-trisopterus-minutus-3210258","Minimum_dyp":10.0,"Maximum_dyp":400.0},"\u00d8yep\u00e5l":{"Familie":"Torskefamilien","Art":"\u00d8yep\u00e5l","Latin":"Trisopterus esmarkii","Lengde":35.0,"Vekt":null,"Norgesrekord":290.0,"Link":"https:\/\/no.wikipedia.org\/wiki\/%C3%98yep%C3%A5l","Link_rekord":"https:\/\/www.klikk.no\/produkthjemmesider\/villmarksliv\/oyepal-trisopterus-esmarkii-3223129","Minimum_dyp":50.0,"Maximum_dyp":300.0},"Lange":{"Familie":"Brosmefamilien","Art":"Lange","Latin":"Molva molva","Lengde":210.0,"Vekt":45000.0,"Norgesrekord":46700.0,"Link":"https:\/\/no.wikipedia.org\/wiki\/Lange","Link_rekord":"https:\/\/www.klikk.no\/produkthjemmesider\/villmarksliv\/lange-molva-molva-2887034","Minimum_dyp":15.0,"Maximum_dyp":1000.0},"Bl\u00e5lange":{"Familie":"Brosmefamilien","Art":"Bl\u00e5lange","Latin":"Molva dypterygia","Lengde":155.0,"Vekt":null,"Norgesrekord":18516.0,"Link":"https:\/\/snl.no\/bl%C3%A5lange","Link_rekord":"https:\/\/www.hooked.no\/artikler\/alf-ronny-blalange-slar-bade-norges-og-verdensrekorden","Minimum_dyp":150.0,"Maximum_dyp":1000.0},"Brosme":{"Familie":"Brosmefamilien","Art":"Brosme","Latin":"Brosme brosme","Lengde":130.0,"Vekt":20000.0,"Norgesrekord":17260.0,"Link":"https:\/\/no.wikipedia.org\/wiki\/Brosme","Link_rekord":"https:\/\/www.hooked.no\/artikler\/dette-er-verdens-storste-brosme","Minimum_dyp":50.0,"Maximum_dyp":1000.0},"Skjellbrosme":{"Familie":"Skjellbrosmefamilien","Art":"Skjellbrosme","Latin":"Phycis blennoides","Lengde":110.0,"Vekt":null,"Norgesrekord":3120.0,"Link":"https:\/\/no.wikipedia.org\/wiki\/Skjellbrosme","Link_rekord":"https:\/\/www.klikk.no\/produkthjemmesider\/villmarksliv\/skjellbrosme-phycis-blennoides-3222038","Minimum_dyp":150.0,"Maximum_dyp":375.0},"Paddetorsk":{"Familie":"Skjellbrosmefamilien","Art":"Paddetorsk","Latin":"Raniceps raninus","Lengde":28.0,"Vekt":null,"Norgesrekord":945.0,"Link":"https:\/\/snl.no\/paddetorsk","Link_rekord":"https:\/\/www.fiskeavisen.no\/daniel-andersen-17-helt-100\/","Minimum_dyp":0.0,"Maximum_dyp":20.0},"Femtr\u00e5det tangbrosme":{"Familie":"Skjellbrosmefamilien","Art":"Femtr\u00e5det tangbrosme","Latin":"Ciliata mustela","Lengde":25.0,"Vekt":null,"Norgesrekord":218.44,"Link":"https:\/\/en.wikipedia.org\/wiki\/Fivebeard_rockling","Link_rekord":null,"Minimum_dyp":0.0,"Maximum_dyp":15.0},"Firetr\u00e5det tangbrosme":{"Familie":"Skjellbrosmefamilien","Art":"Firetr\u00e5det tangbrosme","Latin":"Enchelyopus cimrius","Lengde":41.0,"Vekt":null,"Norgesrekord":65.0,"Link":"https:\/\/en.wikipedia.org\/wiki\/Fourbeard_rockling","Link_rekord":"https:\/\/www.klikk.no\/produkthjemmesider\/villmarksliv\/4-tradet-tangbrosme-rhinonemus-cimbrius-3222898","Minimum_dyp":50.0,"Maximum_dyp":550.0},"Tretr\u00e5det tangbrosme":{"Familie":"Skjellbrosmefamilien","Art":"Tretr\u00e5det tangbrosme","Latin":"Gaidropsarus vulgaris","Lengde":60.0,"Vekt":2000.0,"Norgesrekord":870.0,"Link":"https:\/\/en.wikipedia.org\/wiki\/Three-bearded_rockling","Link_rekord":"https:\/\/www.klikk.no\/produkthjemmesider\/villmarksliv\/3-tradet-tangbrosme-gaidropsarus-vulgaris-3222878","Minimum_dyp":10.0,"Maximum_dyp":150.0},"Strandtangbrosme":{"Familie":"Skjellbrosmefamilien","Art":"Strandtangbrosme","Latin":"Gaidropsarus mediterraneus","Lengde":35.0,"Vekt":null,"Norgesrekord":423.0,"Link":"https:\/\/en.wikipedia.org\/wiki\/Shore_rockling","Link_rekord":"https:\/\/www.fiskeavisen.no\/fant-fikk-norgesrekord\/","Minimum_dyp":0.0,"Maximum_dyp":20.0},"S\u00f8lvtangbrosme":{"Familie":"Skjellbrosmefamilien","Art":"S\u00f8lvtangbrosme","Latin":"Gaidropsarus argentatus","Lengde":45.0,"Vekt":null,"Norgesrekord":null,"Link":"https:\/\/snl.no\/s%C3%B8lvtangbrosme","Link_rekord":null,"Minimum_dyp":150.0,"Maximum_dyp":2000.0},"Nordlig tangbrosme":{"Familie":"Skjellbrosmefamilien","Art":"Nordlig tangbrosme","Latin":"Ciliata septentrionalis","Lengde":20.0,"Vekt":null,"Norgesrekord":70.0,"Link":"https:\/\/snl.no\/tangbrosmer","Link_rekord":null,"Minimum_dyp":10.0,"Maximum_dyp":90.0},"Lysing":{"Familie":"Lysingfamilien","Art":"Lysing","Latin":"Merluccius merluccius","Lengde":140.0,"Vekt":18000.0,"Norgesrekord":13950.0,"Link":"https:\/\/no.wikipedia.org\/wiki\/Lysing","Link_rekord":"https:\/\/www.hooked.no\/artikler\/kjempelysingen-storre-enn-norges-verdens-rekord","Minimum_dyp":100.0,"Maximum_dyp":1000.0},"Mora":{"Familie":"Moridae","Art":"Mora","Latin":"Mora moro","Lengde":80.0,"Vekt":null,"Norgesrekord":2875.0,"Link":"https:\/\/no.wikipedia.org\/wiki\/Mora_(art)","Link_rekord":"https:\/\/www.nrk.no\/trondelag\/jonas-fikk-rekord-mora-pa-kroken-1.14139071","Minimum_dyp":300.0,"Maximum_dyp":2500.0},"Skolest":{"Familie":"Skolestfamilien","Art":"Skolest","Latin":"Coryphaenoides rupestris","Lengde":null,"Vekt":null,"Norgesrekord":3332.0,"Link":"https:\/\/no.wikipedia.org\/wiki\/Skolest","Link_rekord":"https:\/\/www.hooked.no\/artikler\/tommy-fisket-etter-hakjerring-knuste-norgesrekorden-pa-skolest","Minimum_dyp":400.0,"Maximum_dyp":1200.0},"Isgalt":{"Familie":"Skolestfamilien","Art":"Isgalt","Latin":"Macrourus berglax","Lengde":110.0,"Vekt":null,"Norgesrekord":2763.0,"Link":"https:\/\/no.wikipedia.org\/wiki\/Isgalt","Link_rekord":"https:\/\/www.abcnyheter.no\/helse-og-livsstil\/livet\/2018\/07\/20\/195417114\/knuste-36-ar-gammel-verdensrekord-og-19-ar-gammel-norgesrekord-pa-eggakanten","Minimum_dyp":100.0,"Maximum_dyp":800.0},"Vassild":{"Familie":"Vassildfamilien","Art":"Vassild","Latin":"Argentina silus","Lengde":70.0,"Vekt":null,"Norgesrekord":1525.0,"Link":"https:\/\/snl.no\/vassild","Link_rekord":"https:\/\/www.hooked.no\/artikler\/to-potensielle-norgesrekorder-ostlending","Minimum_dyp":140.0,"Maximum_dyp":1440.0},"Str\u00f8msild":{"Familie":"Vassildfamilien","Art":"Str\u00f8msild","Latin":"Argentina sphyraena","Lengde":35.0,"Vekt":null,"Norgesrekord":169.0,"Link":"https:\/\/no.wikipedia.org\/wiki\/S%C3%B8lvfisk","Link_rekord":"https:\/\/www.klikk.no\/produkthjemmesider\/villmarksliv\/stromsild-argentina-sphyraena-3229494","Minimum_dyp":50.0,"Maximum_dyp":700.0},"Lodde":{"Familie":"Kr\u00f8klefamilien","Art":"Lodde","Latin":"Mallotus villosus","Lengde":25.0,"Vekt":null,"Norgesrekord":44.23,"Link":"https:\/\/no.wikipedia.org\/wiki\/Lodde","Link_rekord":null,"Minimum_dyp":0.0,"Maximum_dyp":275.0},"Hav\u00e5l":{"Familie":"Hav\u00e5lfamilien","Art":"Hav\u00e5l","Latin":"Conger conger","Lengde":300.0,"Vekt":110000.0,"Norgesrekord":32850.0,"Link":"https:\/\/no.wikipedia.org\/wiki\/Hav%C3%A5l","Link_rekord":"https:\/\/www.klikk.no\/produkthjemmesider\/villmarksliv\/haval-conger-conger-3215680","Minimum_dyp":0.0,"Maximum_dyp":250.0},"Sild":{"Familie":"Sildefamilien","Art":"Sild","Latin":"Clupea harengus","Lengde":49.0,"Vekt":null,"Norgesrekord":720.0,"Link":"https:\/\/no.wikipedia.org\/wiki\/Sild","Link_rekord":"https:\/\/www.klikk.no\/produkthjemmesider\/villmarksliv\/sild-clupea-harengus-3221956","Minimum_dyp":0.0,"Maximum_dyp":150.0},"Sardin":{"Familie":"Sildefamilien","Art":"Sardin","Latin":"Sardina pilchardus","Lengde":25.0,"Vekt":null,"Norgesrekord":127.7,"Link":"https:\/\/no.wikipedia.org\/wiki\/Sardin","Link_rekord":null,"Minimum_dyp":10.0,"Maximum_dyp":100.0},"Brisling":{"Familie":"Sildefamilien","Art":"Brisling","Latin":"Sprattus sprattus","Lengde":20.0,"Vekt":null,"Norgesrekord":37.0,"Link":"https:\/\/no.wikipedia.org\/wiki\/Brisling","Link_rekord":"https:\/\/www.klikk.no\/produkthjemmesider\/villmarksliv\/brisling-sprattus-sprattus-3209352","Minimum_dyp":10.0,"Maximum_dyp":150.0},"Kloskate":{"Familie":"Skatefamilien","Art":"Kloskate","Latin":"Amblyraja radiata","Lengde":100.0,"Vekt":11000.0,"Norgesrekord":1825.0,"Link":"https:\/\/no.wikipedia.org\/wiki\/Kloskate","Link_rekord":"https:\/\/www.klikk.no\/produkthjemmesider\/villmarksliv\/kloskate-raja-radiata-2883380","Minimum_dyp":20.0,"Maximum_dyp":400.0},"Isskate":{"Familie":"Skatefamilien","Art":"Isskate","Latin":"Amblyraja hyperborea","Lengde":100.0,"Vekt":null,"Norgesrekord":null,"Link":"https:\/\/snl.no\/isskate","Link_rekord":null,"Minimum_dyp":140.0,"Maximum_dyp":2500.0},"Storskate":{"Familie":"Skatefamilien","Art":"Storskate","Latin":"Dipturus batis","Lengde":285.0,"Vekt":115000.0,"Norgesrekord":26200.0,"Link":"https:\/\/snl.no\/storskate","Link_rekord":"https:\/\/www.klikk.no\/produkthjemmesider\/villmarksliv\/storskate-dipturus-batis-3222124","Minimum_dyp":100.0,"Maximum_dyp":200.0},"Hvitskate":{"Familie":"Skatefamilien","Art":"Hvitskate","Latin":"Rajella lintea","Lengde":120.0,"Vekt":null,"Norgesrekord":11490.0,"Link":"https:\/\/snl.no\/hvitskate","Link_rekord":"https:\/\/www.adressa.no\/nyheter\/trondheim\/2016\/08\/16\/Tr%C3%B8nderfiskere-tok-norgesrekord-med-sjelden-fangst-ved-Nordkapp-13186468.ece","Minimum_dyp":150.0,"Maximum_dyp":640.0},"Svartskate":{"Familie":"Skatefamilien","Art":"Svartskate","Latin":"Dipturus nidarosiensis","Lengde":230.0,"Vekt":null,"Norgesrekord":49160.0,"Link":"https:\/\/snl.no\/svartskate","Link_rekord":"https:\/\/www.klikk.no\/produkthjemmesider\/villmarksliv\/svartskate-dipturus-nidarosiensis-3223024","Minimum_dyp":200.0,"Maximum_dyp":1000.0},"Spisskate":{"Familie":"Skatefamilien","Art":"Spisskate","Latin":"Dipturus oxyrinchus","Lengde":150.0,"Vekt":null,"Norgesrekord":16200.0,"Link":"https:\/\/snl.no\/spisskate","Link_rekord":"https:\/\/www.hooked.no\/artikler\/sjekk-vilhelm-sin-rekordstore-spisskate","Minimum_dyp":50.0,"Maximum_dyp":500.0},"Sandskate":{"Familie":"Skatefamilien","Art":"Sandskate","Latin":"Leucoraja circularis","Lengde":130.0,"Vekt":null,"Norgesrekord":5900.0,"Link":"https:\/\/snl.no\/sandskate","Link_rekord":"https:\/\/www.nrk.no\/trondelag\/sandskate-tatt-pa-stang-for-forste-gang-1.12333784","Minimum_dyp":50.0,"Maximum_dyp":800.0},"Nebbskate":{"Familie":"Skatefamilien","Art":"Nebbskate","Latin":"Leucoraja fullonica","Lengde":120.0,"Vekt":null,"Norgesrekord":null,"Link":"https:\/\/snl.no\/nebbskate","Link_rekord":null,"Minimum_dyp":30.0,"Maximum_dyp":550.0},"Piggskate":{"Familie":"Skatefamilien","Art":"Piggskate","Latin":"Raja clavata","Lengde":120.0,"Vekt":null,"Norgesrekord":10750.0,"Link":"https:\/\/snl.no\/piggskate","Link_rekord":"https:\/\/www.klikk.no\/produkthjemmesider\/villmarksliv\/piggskate-raja-clavata-2899577","Minimum_dyp":20.0,"Maximum_dyp":300.0},"Rundskate":{"Familie":"Skatefamilien","Art":"Rundskate","Latin":"Rajella fyllae","Lengde":56.0,"Vekt":null,"Norgesrekord":null,"Link":"https:\/\/snl.no\/rundskate","Link_rekord":null,"Minimum_dyp":170.0,"Maximum_dyp":2050.0},"Havmus":{"Familie":"Havmusfamilien","Art":"Havmus","Latin":"Chimaera monstrosa","Lengde":150.0,"Vekt":null,"Norgesrekord":2950.0,"Link":"https:\/\/no.wikipedia.org\/wiki\/Havmus","Link_rekord":"https:\/\/www.klikk.no\/produkthjemmesider\/villmarksliv\/havmus-chimaera-monstrosa-3210029","Minimum_dyp":40.0,"Maximum_dyp":500.0},"Makrellhai":{"Familie":"Haier","Art":"Makrellhai","Latin":"Isurus oxyrinchus","Lengde":400.0,"Vekt":600000.0,"Norgesrekord":null,"Link":"https:\/\/no.wikipedia.org\/wiki\/Makrellhai","Link_rekord":null,"Minimum_dyp":0.0,"Maximum_dyp":150.0},"H\u00e5brann":{"Familie":"Haier","Art":"H\u00e5brann","Latin":"Lamna nasus","Lengde":300.0,"Vekt":200000.0,"Norgesrekord":43000.0,"Link":"https:\/\/no.wikipedia.org\/wiki\/H%C3%A5brann","Link_rekord":"https:\/\/www.klikk.no\/produkthjemmesider\/villmarksliv\/habrann-lamna-nasus-3211672","Minimum_dyp":10.0,"Maximum_dyp":1000.0},"H\u00e5gjel":{"Familie":"Haier","Art":"H\u00e5gjel","Latin":"Galeus melastomus","Lengde":80.0,"Vekt":null,"Norgesrekord":1950.0,"Link":"https:\/\/no.wikipedia.org\/wiki\/H%C3%A5gjel","Link_rekord":null,"Minimum_dyp":15.0,"Maximum_dyp":1400.0},"Sm\u00e5flekket r\u00f8dhai":{"Familie":"Haier","Art":"Sm\u00e5flekket r\u00f8dhai","Latin":"Scyliorhinus canicula","Lengde":85.0,"Vekt":null,"Norgesrekord":1730.0,"Link":"https:\/\/no.wikipedia.org\/wiki\/Sm%C3%A5flekket_r%C3%B8dhai","Link_rekord":"https:\/\/www.hooked.no\/artikler\/anders-17-knuste-norgesrekorden","Minimum_dyp":10.0,"Maximum_dyp":400.0},"Storflekket r\u00f8dhai":{"Familie":"Haier","Art":"Storflekket r\u00f8dhai","Latin":"Scyliorhinus stellaris","Lengde":160.0,"Vekt":null,"Norgesrekord":4800.0,"Link":"https:\/\/snl.no\/r%C3%B8dhaier","Link_rekord":"https:\/\/www.klikk.no\/produkthjemmesider\/villmarksliv\/storflekket-rodhai-scyliorhinus-stellaris-3221618","Minimum_dyp":20.0,"Maximum_dyp":125.0},"Bl\u00e5hai":{"Familie":"Haier","Art":"Bl\u00e5hai","Latin":"Prionace glauca","Lengde":400.0,"Vekt":210000.0,"Norgesrekord":null,"Link":"https:\/\/snl.no\/bl%C3%A5hai","Link_rekord":null,"Minimum_dyp":0.0,"Maximum_dyp":350.0},"Gr\u00e5hai":{"Familie":"Haier","Art":"Gr\u00e5hai","Latin":"Galeorhinus galeus","Lengde":200.0,"Vekt":45000.0,"Norgesrekord":10600.0,"Link":"https:\/\/snl.no\/gr%C3%A5hai","Link_rekord":"https:\/\/www.klikk.no\/produkthjemmesider\/villmarksliv\/grahai-galeorhinus-galeus-3209594","Minimum_dyp":0.0,"Maximum_dyp":1000.0},"Piggh\u00e5":{"Familie":"Haier","Art":"Piggh\u00e5","Latin":"Squalus acanthias","Lengde":160.0,"Vekt":null,"Norgesrekord":9900.0,"Link":"https:\/\/no.wikipedia.org\/wiki\/Piggh%C3%A5","Link_rekord":"https:\/\/www.klikk.no\/produkthjemmesider\/villmarksliv\/piggha-squalus-acanthias-3215728","Minimum_dyp":0.0,"Maximum_dyp":1400.0},"Svarth\u00e5":{"Familie":"Haier","Art":"Svarth\u00e5","Latin":"Etmopterus spinax","Lengde":50.0,"Vekt":1000.0,"Norgesrekord":960.0,"Link":"https:\/\/no.wikipedia.org\/wiki\/Svarth%C3%A5","Link_rekord":"https:\/\/www.klikk.no\/produkthjemmesider\/villmarksliv\/svartha-etmopterus-spinax-3258264","Minimum_dyp":50.0,"Maximum_dyp":700.0},"H\u00e5kjerring":{"Familie":"Haier","Art":"H\u00e5kjerring","Latin":"Somniosus microcephalus","Lengde":750.0,"Vekt":null,"Norgesrekord":1099000.0,"Link":"https:\/\/no.wikipedia.org\/wiki\/H%C3%A5kjerring","Link_rekord":"https:\/\/www.hooked.no\/artikler\/ny-verdensrekord-pa-hakjerring","Minimum_dyp":200.0,"Maximum_dyp":600.0},"Breiflabb":{"Familie":"Breiflabbfamilien","Art":"Breiflabb","Latin":"Lophius piscatorius","Lengde":200.0,"Vekt":120000.0,"Norgesrekord":63450.0,"Link":"https:\/\/no.wikipedia.org\/wiki\/Breiflabb","Link_rekord":"https:\/\/www.hooked.no\/artikler\/karl-olav-knuste-norgesrekorden","Minimum_dyp":0.0,"Maximum_dyp":2000.0},"Horngjel":{"Familie":"Horngjelfamilien","Art":"Horngjel","Latin":"Belone belone","Lengde":90.0,"Vekt":null,"Norgesrekord":1630.0,"Link":"https:\/\/no.wikipedia.org\/wiki\/Horngjel","Link_rekord":"https:\/\/www.klikk.no\/produkthjemmesider\/villmarksliv\/horngjel-belone-belone-3209629","Minimum_dyp":0.0,"Maximum_dyp":20.0},"S\u00f8lvkveite":{"Familie":"B\u00e5ndfiskfamilien","Art":"S\u00f8lvkveite","Latin":"Trachipterus arcticus","Lengde":300.0,"Vekt":null,"Norgesrekord":8160.0,"Link":"https:\/\/no.wikipedia.org\/wiki\/S%C3%B8lvkveite","Link_rekord":"https:\/\/www.vg.no\/nyheter\/innenriks\/i\/8gm0A\/marco-34-fikk-denne-underlige-fisken-paa-kroken","Minimum_dyp":300.0,"Maximum_dyp":1000.0},"St.Peterfisk":{"Familie":"St.Peterfiskfamilen","Art":"St.Peterfisk","Latin":"Zeus faber","Lengde":65.0,"Vekt":3000.0,"Norgesrekord":2565.0,"Link":"https:\/\/no.wikipedia.org\/wiki\/St._Petersfisk","Link_rekord":"https:\/\/www.klikk.no\/produkthjemmesider\/villmarksliv\/st-petersfisk-zeus-faber-2899637","Minimum_dyp":25.0,"Maximum_dyp":400.0},"Tangstikling":{"Familie":"Stingsildfamilien","Art":"Tangstikling","Latin":"Spinachia spinachia","Lengde":20.0,"Vekt":null,"Norgesrekord":22.0,"Link":"https:\/\/no.wikipedia.org\/wiki\/Tangstikling","Link_rekord":null,"Minimum_dyp":0.0,"Maximum_dyp":5.0},"Stor havn\u00e5l":{"Familie":"N\u00e5lefiskfamilien","Art":"Stor havn\u00e5l","Latin":"Entelurus aequoreus","Lengde":60.0,"Vekt":null,"Norgesrekord":370.0,"Link":"https:\/\/no.wikipedia.org\/wiki\/Stor_havn%C3%A5l","Link_rekord":null,"Minimum_dyp":0.0,"Maximum_dyp":100.0},"Krumsnutet havn\u00e5l":{"Familie":"N\u00e5lefiskfamilien","Art":"Krumsnutet havn\u00e5l","Latin":"Nerophis lumbriciformis","Lengde":17.0,"Vekt":null,"Norgesrekord":null,"Link":"https:\/\/snl.no\/krumsnutet_havn%C3%A5l","Link_rekord":null,"Minimum_dyp":0.0,"Maximum_dyp":30.0},"Liten havn\u00e5l":{"Familie":"N\u00e5lefiskfamilien","Art":"Liten havn\u00e5l","Latin":"Nerophis ophidion","Lengde":30.0,"Vekt":null,"Norgesrekord":null,"Link":"https:\/\/snl.no\/liten_havn%C3%A5l","Link_rekord":null,"Minimum_dyp":0.0,"Maximum_dyp":25.0},"Stor kantn\u00e5l":{"Familie":"N\u00e5lefiskfamilien","Art":"Stor kantn\u00e5l","Latin":"Syngnathus acus","Lengde":47.0,"Vekt":null,"Norgesrekord":79.7,"Link":"https:\/\/snl.no\/kantn%C3%A5ler","Link_rekord":null,"Minimum_dyp":0.0,"Maximum_dyp":110.0},"Liten kantn\u00e5l":{"Familie":"N\u00e5lefiskfamilien","Art":"Liten kantn\u00e5l","Latin":"Syngnathus rostellatus","Lengde":18.0,"Vekt":null,"Norgesrekord":2.19,"Link":"https:\/\/snl.no\/kantn%C3%A5ler","Link_rekord":null,"Minimum_dyp":0.0,"Maximum_dyp":15.0},"Tangsnelle":{"Familie":"N\u00e5lefiskfamilien","Art":"Tangsnelle","Latin":"Syngnathus typhle","Lengde":25.0,"Vekt":null,"Norgesrekord":22.94,"Link":"https:\/\/snl.no\/tangsnelle","Link_rekord":null,"Minimum_dyp":0.0,"Maximum_dyp":20.0},"Bl\u00e5kjeft":{"Familie":"Uerfamilien","Art":"Bl\u00e5kjeft","Latin":"Helicolenus dactylopterus","Lengde":47.0,"Vekt":null,"Norgesrekord":2056.0,"Link":"https:\/\/no.wikipedia.org\/wiki\/Bl%C3%A5kjeft","Link_rekord":null,"Minimum_dyp":150.0,"Maximum_dyp":600.0},"Uer":{"Familie":"Uerfamilien","Art":"Uer","Latin":"Sebastes norvegicus","Lengde":100.0,"Vekt":15000.0,"Norgesrekord":12140.0,"Link":"https:\/\/no.wikipedia.org\/wiki\/Vanlig_uer","Link_rekord":"https:\/\/www.klikk.no\/produkthjemmesider\/villmarksliv\/uer-sebastes-marinus-2899607","Minimum_dyp":100.0,"Maximum_dyp":500.0},"Snabeluer":{"Familie":"Uerfamilien","Art":"Snabeluer","Latin":"Sebastes mentella","Lengde":72.0,"Vekt":null,"Norgesrekord":1059.0,"Link":"https:\/\/no.wikipedia.org\/wiki\/Snabeluer","Link_rekord":"https:\/\/www.klikk.no\/produkthjemmesider\/villmarksliv\/snabeluer-sebastes-mentella-3222064","Minimum_dyp":300.0,"Maximum_dyp":1000.0},"Lusuer":{"Familie":"Uerfamilien","Art":"Lusuer","Latin":"Sebastes viviparus","Lengde":35.0,"Vekt":null,"Norgesrekord":777.0,"Link":"https:\/\/no.wikipedia.org\/wiki\/Lusuer","Link_rekord":"https:\/\/www.klikk.no\/produkthjemmesider\/villmarksliv\/lusuer-sebastes-viviparus-3211926","Minimum_dyp":10.0,"Maximum_dyp":200.0},"Marmorert berguer":{"Familie":"Uerfamilien","Art":"Marmorert berguer","Latin":"Sebastiscus marmoratus","Lengde":null,"Vekt":null,"Norgesrekord":440.0,"Link":"https:\/\/snl.no\/marmorert_berguer","Link_rekord":"https:\/\/www.hooked.no\/artikler\/den-ukjente-fisken-er-identifisert-mot-den-marmorerte-bergueren","Minimum_dyp":null,"Maximum_dyp":null},"Vanlig knurr":{"Familie":"Knurrfamilien","Art":"Vanlig knurr","Latin":"Eutrigla gurnardus","Lengde":60.0,"Vekt":1200.0,"Norgesrekord":1093.0,"Link":"https:\/\/no.m.wikipedia.org\/wiki\/Knurr","Link_rekord":null,"Minimum_dyp":0.0,"Maximum_dyp":150.0},"R\u00f8dknurr":{"Familie":"Knurrfamilien","Art":"R\u00f8dknurr","Latin":"Chelidonichthys lucerna","Lengde":75.0,"Vekt":5200.0,"Norgesrekord":1648.0,"Link":"https:\/\/en.m.wikipedia.org\/wiki\/Tub_gurnard","Link_rekord":"https:\/\/www.klikk.no\/produkthjemmesider\/villmarksliv\/rodknurr-chelidonichthys-lucernus-3221628","Minimum_dyp":0.0,"Maximum_dyp":150.0},"Krokulke":{"Familie":"Ulkefamilien","Art":"Krokulke","Latin":"Artediellus atlanticus","Lengde":15.0,"Vekt":null,"Norgesrekord":30.4,"Link":"https:\/\/snl.no\/krokulke","Link_rekord":null,"Minimum_dyp":35.0,"Maximum_dyp":900.0},"Glattulke":{"Familie":"Ulkefamilien","Art":"Glattulke","Latin":"Gymnocanthus tricuspis","Lengde":21.0,"Vekt":null,"Norgesrekord":240.0,"Link":"https:\/\/snl.no\/glattulke","Link_rekord":"https:\/\/www.klikk.no\/produkthjemmesider\/villmarksliv\/glattulke-gymnocanthus-tricuspis-3209564","Minimum_dyp":10.0,"Maximum_dyp":240.0},"Piggulke":{"Familie":"Ulkefamilien","Art":"Piggulke","Latin":"Micrenophrys lilljeborgii","Lengde":7.5,"Vekt":null,"Norgesrekord":4.0,"Link":"https:\/\/no.m.wikipedia.org\/wiki\/Piggulke","Link_rekord":null,"Minimum_dyp":0.0,"Maximum_dyp":100.0},"Vanlig ulke":{"Familie":"Ulkefamilien","Art":"Vanlig ulke","Latin":"Myoxocephalus scorpius","Lengde":60.0,"Vekt":null,"Norgesrekord":850.0,"Link":"https:\/\/no.m.wikipedia.org\/wiki\/Vanlig_ulke","Link_rekord":"https:\/\/www.klikk.no\/produkthjemmesider\/villmarksliv\/ulke-myoxocephalus-scorpius-3223054","Minimum_dyp":0.0,"Maximum_dyp":110.0},"Dvergulke":{"Familie":"Ulkefamilien","Art":"Dvergulke","Latin":"Taurulus bubalis","Lengde":17.0,"Vekt":null,"Norgesrekord":175.8,"Link":"https:\/\/no.m.wikipedia.org\/wiki\/Dvergulke","Link_rekord":null,"Minimum_dyp":0.0,"Maximum_dyp":30.0},"Nordlig knurrulke":{"Familie":"Ulkefamilien","Art":"Nordlig knurrulke","Latin":"Triglops murrayi","Lengde":17.0,"Vekt":null,"Norgesrekord":47.4,"Link":"https:\/\/snl.no\/nordlig_knurrulke","Link_rekord":null,"Minimum_dyp":50.0,"Maximum_dyp":250.0},"Arktisk knurrulke":{"Familie":"Ulkefamilien","Art":"Arktisk knurrulke","Latin":"Triglops pingelii","Lengde":20.0,"Vekt":null,"Norgesrekord":92.0,"Link":"https:\/\/snl.no\/arktisk_knurrulke","Link_rekord":"https:\/\/www.klikk.no\/produkthjemmesider\/villmarksliv\/arktisk-knurrulke-triglops-pingelii-3211894","Minimum_dyp":0.0,"Maximum_dyp":200.0},"Vanlig ringbuk":{"Familie":"Ringbuker","Art":"Vanlig ringbuk","Latin":"Liparis liparis","Lengde":15.0,"Vekt":null,"Norgesrekord":2.0,"Link":"https:\/\/no.wikipedia.org\/wiki\/Vanlig_ringbuk","Link_rekord":"https:\/\/www.klikk.no\/produkthjemmesider\/villmarksliv\/ringbuk-liparis-liparis-3221547","Minimum_dyp":0.0,"Maximum_dyp":100.0},"Kystringbuk":{"Familie":"Ringbuker","Art":"Kystringbuk","Latin":"Liparis montagui","Lengde":12.0,"Vekt":null,"Norgesrekord":8.5,"Link":"https:\/\/no.wikipedia.org\/wiki\/Kystringbuk","Link_rekord":null,"Minimum_dyp":0.0,"Maximum_dyp":30.0},"Panserulke":{"Familie":"Panserulkefamilien","Art":"Panserulke","Latin":"Agonus cataphractus","Lengde":21.0,"Vekt":null,"Norgesrekord":50.7,"Link":"https:\/\/snl.no\/panserulke","Link_rekord":null,"Minimum_dyp":0.0,"Maximum_dyp":20.0},"Tiskjegg":{"Familie":"Panserulkefamilien","Art":"Tiskjegg","Latin":"Leptagonus decagonus","Lengde":21.0,"Vekt":null,"Norgesrekord":4.2,"Link":"https:\/\/snl.no\/tiskjegg","Link_rekord":"https:\/\/www.nrk.no\/finnmark\/denne-fire-gram-tunge-fisken-er-trolig-en-sensasjon-1.14271252","Minimum_dyp":0.0,"Maximum_dyp":930.0},"Vanlig rognkjeks":{"Familie":"Rognkjeksfamilien","Art":"Vanlig rognkjeks","Latin":"Cyclopterus lumpus","Lengde":60.0,"Vekt":10000.0,"Norgesrekord":8635.0,"Link":"https:\/\/snl.no\/rognkjeks","Link_rekord":"https:\/\/www.klikk.no\/produkthjemmesider\/villmarksliv\/rognkjeks-cyclopterus-lumpus-3221557","Minimum_dyp":0.0,"Maximum_dyp":150.0},"Vortekjeks":{"Familie":"Rognkjeksfamilien","Art":"Vortekjeks","Latin":"Eumicrotremus spinosus","Lengde":13.0,"Vekt":null,"Norgesrekord":null,"Link":"https:\/\/snl.no\/vortekjeks","Link_rekord":null,"Minimum_dyp":60.0,"Maximum_dyp":400.0},"Havabbor":{"Familie":"Havabborfamilien","Art":"Havabbor","Latin":"Dicentrarchus labrax","Lengde":100.0,"Vekt":12000.0,"Norgesrekord":6170.0,"Link":"https:\/\/snl.no\/havabbor","Link_rekord":null,"Minimum_dyp":0.0,"Maximum_dyp":20.0},"Taggmakrell":{"Familie":"Taggmakrellfamilien","Art":"Taggmakrell","Latin":"Trachurus trachurus","Lengde":70.0,"Vekt":null,"Norgesrekord":1163.0,"Link":"https:\/\/snl.no\/taggmakrell","Link_rekord":"https:\/\/www.klikk.no\/produkthjemmesider\/villmarksliv\/taggmakrell-trachurus-trachurus-3222888","Minimum_dyp":0.0,"Maximum_dyp":100.0},"Havbrasme":{"Familie":"Havbrasmefamilien","Art":"Havbrasme","Latin":"Brama brama","Lengde":100.0,"Vekt":6000.0,"Norgesrekord":1980.0,"Link":"https:\/\/no.m.wikipedia.org\/wiki\/Havbrasme","Link_rekord":"https:\/\/www.klikk.no\/produkthjemmesider\/villmarksliv\/havbrasme-brama-brama-3210019","Minimum_dyp":100.0,"Maximum_dyp":300.0},"S\u00f8lvbrasme":{"Familie":"Havbrasmefamilien","Art":"S\u00f8lvbrasme","Latin":"Pterycombus brama","Lengde":46.0,"Vekt":null,"Norgesrekord":null,"Link":"https:\/\/no.m.wikipedia.org\/wiki\/S\u00f8lvbrasme","Link_rekord":null,"Minimum_dyp":25.0,"Maximum_dyp":400.0},"Mulle":{"Familie":"Mullefamilien","Art":"Mulle","Latin":"Mullus surmuletus","Lengde":40.0,"Vekt":1000.0,"Norgesrekord":75.0,"Link":"https:\/\/no.m.wikipedia.org\/wiki\/Mulle","Link_rekord":"https:\/\/www.klikk.no\/produkthjemmesider\/villmarksliv\/mulle-mullus-surmuletus-3212234","Minimum_dyp":0.0,"Maximum_dyp":100.0},"Tykkleppet multe":{"Familie":"Multefamilien","Art":"Tykkleppet multe","Latin":"Chelon labrosus","Lengde":75.0,"Vekt":4500.0,"Norgesrekord":4820.0,"Link":"https:\/\/no.m.wikipedia.org\/wiki\/Tykkleppet_multe","Link_rekord":"https:\/\/www.klikk.no\/produkthjemmesider\/villmarksliv\/tykkleppet-multe-chelon-labrosus-3223044","Minimum_dyp":0.0,"Maximum_dyp":20.0},"Brungylt":{"Familie":"Berggyltfamilien","Art":"Brungylt","Latin":"Acantholabrus palloni","Lengde":25.0,"Vekt":null,"Norgesrekord":408.0,"Link":"https:\/\/no.m.wikipedia.org\/wiki\/Brungylt","Link_rekord":null,"Minimum_dyp":30.0,"Maximum_dyp":270.0},"Gressgylt":{"Familie":"Berggyltfamilien","Art":"Gressgylt","Latin":"Centrolabrus exoletus","Lengde":18.0,"Vekt":null,"Norgesrekord":116.0,"Link":"https:\/\/no.m.wikipedia.org\/wiki\/Gressgylt","Link_rekord":"https:\/\/www.klikk.no\/produkthjemmesider\/villmarksliv\/gressgylt-centrolabrus-exoletus-3209574","Minimum_dyp":0.0,"Maximum_dyp":25.0},"Bergnebb":{"Familie":"Berggyltfamilien","Art":"Bergnebb","Latin":"Ctenolabrus rupestris","Lengde":18.0,"Vekt":null,"Norgesrekord":134.5,"Link":"https:\/\/snl.no\/bergnebb","Link_rekord":null,"Minimum_dyp":0.0,"Maximum_dyp":50.0},"Berggylt":{"Familie":"Berggyltfamilien","Art":"Berggylt","Latin":"Labrus bergylta","Lengde":65.0,"Vekt":5000.0,"Norgesrekord":2376.0,"Link":"https:\/\/snl.no\/berggylt","Link_rekord":"https:\/\/www.klikk.no\/produkthjemmesider\/villmarksliv\/berggylte-labrus-bergylta-3267491","Minimum_dyp":0.0,"Maximum_dyp":50.0},"Bl\u00e5st\u00e5l":{"Familie":"Berggyltfamilien","Art":"Bl\u00e5st\u00e5l","Latin":"Labrus mixtus","Lengde":40.0,"Vekt":1100.0,"Norgesrekord":1050.0,"Link":"https:\/\/no.m.wikipedia.org\/wiki\/Bl\u00e5st\u00e5l","Link_rekord":null,"Minimum_dyp":5.0,"Maximum_dyp":200.0},"Gr\u00f8nngylt":{"Familie":"Berggyltfamilien","Art":"Gr\u00f8nngylt","Latin":"Symphodus melops","Lengde":25.0,"Vekt":null,"Norgesrekord":271.0,"Link":"https:\/\/no.m.wikipedia.org\/wiki\/Gr\u00f8nngylt","Link_rekord":"https:\/\/www.klikk.no\/produkthjemmesider\/villmarksliv\/gronngylt-symphodus-melops-3209584","Minimum_dyp":0.0,"Maximum_dyp":30.0},"Vanlig \u00e5lebrosme":{"Familie":"\u00c5lekvabbefamilien","Art":"Vanlig \u00e5lebrosme","Latin":"Lycodes vahlii","Lengde":53.0,"Vekt":null,"Norgesrekord":96.0,"Link":"https:\/\/no.m.wikipedia.org\/wiki\/Vanlig_\u00e5lebrosme","Link_rekord":"https:\/\/www.nrk.no\/troms\/kim-eirik-fanget-sjelden-fisk-1.12176114","Minimum_dyp":50.0,"Maximum_dyp":600.0},"Nordlig \u00e5lebrosme":{"Familie":"\u00c5lekvabbefamilien","Art":"Nordlig \u00e5lebrosme","Latin":"Lycodes rossi","Lengde":31.0,"Vekt":null,"Norgesrekord":28.2,"Link":"https:\/\/snl.no\/\u00e5lebrosmer","Link_rekord":"https:\/\/www.nrk.no\/finnmark\/forst-i-verden-med-sensasjonell-fangst-1.14099592","Minimum_dyp":45.0,"Maximum_dyp":350.0},"\u00c5lekvabbe":{"Familie":"\u00c5lekvabbefamilien","Art":"\u00c5lekvabbe","Latin":"Zoarces viviparus","Lengde":50.0,"Vekt":null,"Norgesrekord":560.0,"Link":"https:\/\/snl.no\/\u00e5lekvabbe","Link_rekord":"https:\/\/www.klikk.no\/produkthjemmesider\/villmarksliv\/alekvabbe-zoarces-viviparus-3223139","Minimum_dyp":0.0,"Maximum_dyp":20.0},"Hornkvabbe":{"Familie":"Hornkvabbefamilien","Art":"Hornkvabbe","Latin":"Chirolophis ascanii","Lengde":25.0,"Vekt":null,"Norgesrekord":113.4,"Link":"https:\/\/snl.no\/hornkvabbe","Link_rekord":"https:\/\/www.hooked.no\/artikler\/to-potensielle-norgesrekorder-ostlending","Minimum_dyp":0.0,"Maximum_dyp":175.0},"Langhalet langebarn":{"Familie":"Hornkvabbefamilien","Art":"Langhalet langebarn","Latin":"Lumpenus lampretaeformis","Lengde":50.0,"Vekt":null,"Norgesrekord":48.3,"Link":"https:\/\/no.m.wikipedia.org\/wiki\/Langhalet_langebarn","Link_rekord":null,"Minimum_dyp":50.0,"Maximum_dyp":200.0},"Tverrhalet langebarn":{"Familie":"Hornkvabbefamilien","Art":"Tverrhalet langebarn","Latin":"Leptoclinus maculatus","Lengde":20.0,"Vekt":null,"Norgesrekord":8.2,"Link":"https:\/\/snl.no\/langebarn","Link_rekord":"https:\/\/www.hooked.no\/artikler\/sensasjonelle-fangster-fra-finnmark-de-forste-stangfangstene-i-verden","Minimum_dyp":15.0,"Maximum_dyp":400.0},"Tangsprell":{"Familie":"Tangsprellfamilien","Art":"Tangsprell","Latin":"Pholis gunnellus","Lengde":30.0,"Vekt":null,"Norgesrekord":50.8,"Link":"https:\/\/no.m.wikipedia.org\/wiki\/Tangsprell","Link_rekord":null,"Minimum_dyp":0.0,"Maximum_dyp":100.0},"Gr\u00e5steinbit":{"Familie":"Steinbitfamilien","Art":"Gr\u00e5steinbit","Latin":"Anarhichas lupus","Lengde":150.0,"Vekt":23000.0,"Norgesrekord":18350.0,"Link":"https:\/\/snl.no\/gr\u00e5steinbit","Link_rekord":null,"Minimum_dyp":20.0,"Maximum_dyp":500.0},"Bl\u00e5steinbit":{"Familie":"Steinbitfamilien","Art":"Bl\u00e5steinbit","Latin":"Anarhichas denticulatus","Lengde":150.0,"Vekt":25000.0,"Norgesrekord":25150.0,"Link":"https:\/\/no.m.wikipedia.org\/wiki\/Bl\u00e5steinbit","Link_rekord":"https:\/\/www.abcnyheter.no\/helse-og-livsstil\/livet\/2018\/07\/20\/195417114\/knuste-36-ar-gammel-verdensrekord-og-19-ar-gammel-norgesrekord-pa-eggakanten","Minimum_dyp":300.0,"Maximum_dyp":1000.0},"Flekksteinbit":{"Familie":"Steinbitfamilien","Art":"Flekksteinbit","Latin":"Anarchichas minor","Lengde":180.0,"Vekt":26000.0,"Norgesrekord":27900.0,"Link":"https:\/\/snl.no\/flekksteinbit","Link_rekord":"https:\/\/www.klikk.no\/produkthjemmesider\/villmarksliv\/flekksteinbit-anarhichas-minor-3209524","Minimum_dyp":25.0,"Maximum_dyp":800.0},"Fjesing":{"Familie":"Fjesingfamilien","Art":"Fjesing","Latin":"Trachinus draco","Lengde":40.0,"Vekt":null,"Norgesrekord":650.0,"Link":"https:\/\/no.m.wikipedia.org\/wiki\/Fjesing","Link_rekord":"https:\/\/www.klikk.no\/produkthjemmesider\/villmarksliv\/fjesing-trachinus-draco-3209534","Minimum_dyp":0.0,"Maximum_dyp":150.0},"Tangkvabbe":{"Familie":"Tangkvabbefamilien","Art":"Tangkvabbe","Latin":"Lipophrys pholis","Lengde":18.0,"Vekt":null,"Norgesrekord":87.0,"Link":"https:\/\/no.m.wikipedia.org\/wiki\/Tangkvabbe","Link_rekord":null,"Minimum_dyp":0.0,"Maximum_dyp":30.0},"Havsil":{"Familie":"Silfamilien","Art":"Havsil","Latin":"Ammodytes marinus","Lengde":24.0,"Vekt":null,"Norgesrekord":5.6,"Link":"https:\/\/no.m.wikipedia.org\/wiki\/Havsil","Link_rekord":"https:\/\/www.fiskeavisen.no\/daniel-andersen-med-norgesrekord-og-er-william-5-norges-yngste-til-a-fiske-havsil-pa-stang\/","Minimum_dyp":10.0,"Maximum_dyp":40.0},"Sm\u00e5sil":{"Familie":"Silfamilien","Art":"Sm\u00e5sil","Latin":"Ammodytes tobianus","Lengde":20.0,"Vekt":null,"Norgesrekord":24.1,"Link":"https:\/\/no.m.wikipedia.org\/wiki\/Sm\u00e5sil","Link_rekord":null,"Minimum_dyp":0.0,"Maximum_dyp":30.0},"Storsil":{"Familie":"Silfamilien","Art":"Storsil","Latin":"Hyperoplus lanceolatus","Lengde":40.0,"Vekt":null,"Norgesrekord":190.0,"Link":"https:\/\/snl.no\/storsil","Link_rekord":"https:\/\/www.klikk.no\/produkthjemmesider\/villmarksliv\/storsil-hyperoplus-lanceolatus-3222114","Minimum_dyp":0.0,"Maximum_dyp":30.0},"Vanlig fl\u00f8yfisk":{"Familie":"Fl\u00f8yfiskfamilien","Art":"Vanlig fl\u00f8yfisk","Latin":"Callionymus lyra","Lengde":30.0,"Vekt":null,"Norgesrekord":209.0,"Link":"https:\/\/no.m.wikipedia.org\/wiki\/Vanlig_fl\u00f8yfisk","Link_rekord":"https:\/\/www.klikk.no\/produkthjemmesider\/villmarksliv\/floyfisk-callionymus-lyra-2899617","Minimum_dyp":0.0,"Maximum_dyp":200.0},"Flekket fl\u00f8yfisk":{"Familie":"Fl\u00f8yfiskfamilien","Art":"Flekket fl\u00f8yfisk","Latin":"Callionymus maculatus","Lengde":16.0,"Vekt":null,"Norgesrekord":12.8,"Link":"https:\/\/snl.no\/flekket_fl\u00f8yfisk","Link_rekord":"https:\/\/www.klikk.no\/produkthjemmesider\/villmarksliv\/flekket-floyfisk-callionymus-maculatus-3209514","Minimum_dyp":70.0,"Maximum_dyp":300.0},"Liten fl\u00f8yfisk":{"Familie":"Fl\u00f8yfiskfamilien","Art":"Liten fl\u00f8yfisk","Latin":"Callionymus reticulatus","Lengde":11.0,"Vekt":null,"Norgesrekord":17.46,"Link":"https:\/\/snl.no\/liten_fl\u00f8yfisk","Link_rekord":null,"Minimum_dyp":0.0,"Maximum_dyp":40.0},"Glasskutling":{"Familie":"Kutlingfamilien","Art":"Glasskutling","Latin":"Aphia minuta","Lengde":8.0,"Vekt":null,"Norgesrekord":1.1,"Link":"https:\/\/no.m.wikipedia.org\/wiki\/Glasskutling","Link_rekord":null,"Minimum_dyp":0.0,"Maximum_dyp":80.0},"Piggkutling":{"Familie":"Kutlingfamilien","Art":"Piggkutling","Latin":"Buenia jeffreysi","Lengde":6.0,"Vekt":null,"Norgesrekord":null,"Link":"https:\/\/no.m.wikipedia.org\/wiki\/Piggkutling","Link_rekord":null,"Minimum_dyp":5.0,"Maximum_dyp":330.0},"Krystallkutling":{"Familie":"Kutlingfamilien","Art":"Krystallkutling","Latin":"Crystallogobius linearis","Lengde":5.0,"Vekt":null,"Norgesrekord":0.45,"Link":"https:\/\/no.m.wikipedia.org\/wiki\/Krystallkutling","Link_rekord":"https:\/\/www.fiskeavisen.no\/full-jubel-og-kanskje-norgesrekord-med-denne-fisken\/","Minimum_dyp":0.0,"Maximum_dyp":80.0},"Svartkutling":{"Familie":"Kutlingfamilien","Art":"Svartkutling","Latin":"Gobius niger","Lengde":18.0,"Vekt":null,"Norgesrekord":76.7,"Link":"https:\/\/no.m.wikipedia.org\/wiki\/Svartkutling","Link_rekord":"https:\/\/www.fiskeavisen.no\/ny-norges-rekord-pa-svartkutling\/","Minimum_dyp":0.0,"Maximum_dyp":75.0},"Tangkutling":{"Familie":"Kutlingfamilien","Art":"Tangkutling","Latin":"Gobiusculus flavescens","Lengde":6.0,"Vekt":null,"Norgesrekord":2.52,"Link":"https:\/\/no.m.wikipedia.org\/wiki\/Tangkutling","Link_rekord":null,"Minimum_dyp":0.0,"Maximum_dyp":20.0},"Ulkekutling":{"Familie":"Kutlingfamilien","Art":"Ulkekutling","Latin":"Lebetus scorpioides","Lengde":4.0,"Vekt":null,"Norgesrekord":null,"Link":"https:\/\/no.m.wikipedia.org\/wiki\/Ulkekutling","Link_rekord":null,"Minimum_dyp":30.0,"Maximum_dyp":375.0},"Spisshalet kutling":{"Familie":"Kutlingfamilien","Art":"Spisshalet kutling","Latin":"Lesueurigobius friesii","Lengde":13.0,"Vekt":null,"Norgesrekord":7.8,"Link":"https:\/\/no.m.wikipedia.org\/wiki\/Spisshalet_kutling","Link_rekord":null,"Minimum_dyp":10.0,"Maximum_dyp":350.0},"Leirkutling":{"Familie":"Kutlingfamilien","Art":"Leirkutling","Latin":"Pomatoschistus microps","Lengde":9.0,"Vekt":null,"Norgesrekord":2.97,"Link":"https:\/\/no.m.wikipedia.org\/wiki\/Leirkutling","Link_rekord":"https:\/\/www.fiskeavisen.no\/denne-vesle-fisken-er-norgesrekord\/","Minimum_dyp":0.0,"Maximum_dyp":30.0},"Sandkutling":{"Familie":"Kutlingfamilien","Art":"Sandkutling","Latin":"Pomatoschistus minutus","Lengde":11.0,"Vekt":null,"Norgesrekord":10.0,"Link":"https:\/\/no.m.wikipedia.org\/wiki\/Sandkutling","Link_rekord":null,"Minimum_dyp":0.0,"Maximum_dyp":20.0},"Mudderkutling":{"Familie":"Kutlingfamilien","Art":"Mudderkutling","Latin":"Pomatoschistus norvegicus","Lengde":8.0,"Vekt":null,"Norgesrekord":null,"Link":"https:\/\/no.m.wikipedia.org\/wiki\/Mudderkutling","Link_rekord":null,"Minimum_dyp":30.0,"Maximum_dyp":325.0},"Bergkutling":{"Familie":"Kutlingfamilien","Art":"Bergkutling","Latin":"Pomatoschistus pictus","Lengde":9.0,"Vekt":null,"Norgesrekord":1.5,"Link":"https:\/\/no.m.wikipedia.org\/wiki\/Bergkutling","Link_rekord":null,"Minimum_dyp":0.0,"Maximum_dyp":50.0},"R\u00f8dflekket kutling":{"Familie":"Kutlingfamilien","Art":"R\u00f8dflekket kutling","Latin":"Thorogobius ephippiatus","Lengde":13.0,"Vekt":null,"Norgesrekord":35.8,"Link":"https:\/\/no.wikipedia.org\/wiki\/R%C3%B8dflekket_kutling","Link_rekord":null,"Minimum_dyp":0.0,"Maximum_dyp":40.0},"Auxid":{"Familie":"Makrellfamilien","Art":"Auxid","Latin":"Auxis rochei","Lengde":61.0,"Vekt":3000.0,"Norgesrekord":1500.0,"Link":"https:\/\/no.wikipedia.org\/wiki\/Auxid","Link_rekord":"https:\/\/www.nrk.no\/ostfold\/fisket-etter-makrell-_-fikk-sjelden-fangst-1.13605764","Minimum_dyp":0.0,"Maximum_dyp":50.0},"Stripet pelamide":{"Familie":"Makrellfamilien","Art":"Stripet pelamide","Latin":"Sarda sarda","Lengde":75.0,"Vekt":5400.0,"Norgesrekord":2885.0,"Link":"https:\/\/no.wikipedia.org\/wiki\/Stripet_pelamide","Link_rekord":"https:\/\/www.fiskeavisen.no\/ny-norgesrekord-pa-stripet-pelamide-bonito\/","Minimum_dyp":0.0,"Maximum_dyp":200.0},"Makrell":{"Familie":"Makrellfamilien","Art":"Makrell","Latin":"Scomber scombrus","Lengde":66.0,"Vekt":3500.0,"Norgesrekord":3474.0,"Link":"https:\/\/no.wikipedia.org\/wiki\/Makrell","Link_rekord":"https:\/\/www.klikk.no\/produkthjemmesider\/villmarksliv\/makrell-scomber-scombrus-3212196","Minimum_dyp":0.0,"Maximum_dyp":250.0},"Makrellst\u00f8rje":{"Familie":"Makrellfamilien","Art":"Makrellst\u00f8rje","Latin":"Thunnus thynnus","Lengde":450.0,"Vekt":700000.0,"Norgesrekord":null,"Link":"https:\/\/no.wikipedia.org\/wiki\/Makrellst%C3%B8rje","Link_rekord":null,"Minimum_dyp":0.0,"Maximum_dyp":100.0},"Glassvar":{"Familie":"Varfamilien","Art":"Glassvar","Latin":"Lepidorhombus whiffiagonis","Lengde":60.0,"Vekt":3000.0,"Norgesrekord":2360.0,"Link":"https:\/\/no.wikipedia.org\/wiki\/Glassvar","Link_rekord":"https:\/\/www.klikk.no\/produkthjemmesider\/villmarksliv\/glassvar-lepidorhombus-whiffiagonis-3209544","Minimum_dyp":50.0,"Maximum_dyp":700.0},"Piggvar":{"Familie":"Varfamilien","Art":"Piggvar","Latin":"Psetta maxima","Lengde":100.0,"Vekt":25000.0,"Norgesrekord":13200.0,"Link":"https:\/\/no.wikipedia.org\/wiki\/Piggvar","Link_rekord":"https:\/\/www.klikk.no\/produkthjemmesider\/villmarksliv\/piggvar-psetta-maxima-3221531","Minimum_dyp":0.0,"Maximum_dyp":100.0},"Slettvar":{"Familie":"Varfamilien","Art":"Slettvar","Latin":"Scophthalmus rhombus","Lengde":75.0,"Vekt":8000.0,"Norgesrekord":3860.0,"Link":"https:\/\/no.wikipedia.org\/wiki\/Slettvar","Link_rekord":"https:\/\/www.nrk.no\/sorlandet\/fanget-drommefisken_-_-hjertet-mitt-stoppet-nesten-1.13450509","Minimum_dyp":0.0,"Maximum_dyp":70.0},"Sm\u00e5var":{"Familie":"Varfamilien","Art":"Sm\u00e5var","Latin":"Phrynorhombus norvegicus","Lengde":13.0,"Vekt":null,"Norgesrekord":11.14,"Link":"https:\/\/no.wikipedia.org\/wiki\/Sm%C3%A5var","Link_rekord":"https:\/\/sfk-galskap.no\/pasketur-til-stavanger\/","Minimum_dyp":10.0,"Maximum_dyp":200.0},"H\u00e5rvar":{"Familie":"Varfamilien","Art":"H\u00e5rvar","Latin":"Zeugopterus punctatus","Lengde":25.0,"Vekt":null,"Norgesrekord":318.8,"Link":"https:\/\/no.wikipedia.org\/wiki\/H%C3%A5rvar","Link_rekord":null,"Minimum_dyp":0.0,"Maximum_dyp":40.0},"Tungevar":{"Familie":"Tungevarfamilien","Art":"Tungevar","Latin":"Arnoglossus laterna","Lengde":19.0,"Vekt":null,"Norgesrekord":45.74,"Link":"https:\/\/snl.no\/tungevar","Link_rekord":"https:\/\/www.klikk.no\/produkthjemmesider\/villmarksliv\/tungevar-arnoglossus-laterna-2883438","Minimum_dyp":0.0,"Maximum_dyp":200.0},"Sm\u00f8rflyndre":{"Familie":"Flyndrefamilien","Art":"Sm\u00f8rflyndre","Latin":"Glyptocephalus cynoglossus","Lengde":62.0,"Vekt":2500.0,"Norgesrekord":757.0,"Link":"https:\/\/snl.no\/sm%C3%B8rflyndre","Link_rekord":"https:\/\/www.klikk.no\/produkthjemmesider\/villmarksliv\/smorflyndre-glyptocephalus-cynoglossus-3222074","Minimum_dyp":40.0,"Maximum_dyp":1500.0},"Kveite":{"Familie":"Flyndrefamilien","Art":"Kveite","Latin":"Hippoglossus hippoglossus","Lengde":400.0,"Vekt":300000.0,"Norgesrekord":233500.0,"Link":"https:\/\/no.wikipedia.org\/wiki\/Kveite","Link_rekord":"https:\/\/www.klikk.no\/produkthjemmesider\/villmarksliv\/kveite-hippoglossus-hippoglossus-3242792","Minimum_dyp":10.0,"Maximum_dyp":2000.0},"Gapeflyndre":{"Familie":"Flyndrefamilien","Art":"Gapeflyndre","Latin":"Hippoglossoides platessoides","Lengde":52.0,"Vekt":null,"Norgesrekord":1240.0,"Link":"https:\/\/no.wikipedia.org\/wiki\/Gapeflyndre","Link_rekord":null,"Minimum_dyp":10.0,"Maximum_dyp":500.0},"Sandflyndre":{"Familie":"Flyndrefamilien","Art":"Sandflyndre","Latin":"Limanda limanda","Lengde":42.0,"Vekt":1300.0,"Norgesrekord":1210.0,"Link":"https:\/\/no.wikipedia.org\/wiki\/Sandflyndre","Link_rekord":null,"Minimum_dyp":0.0,"Maximum_dyp":200.0},"Lomre":{"Familie":"Flyndrefamilien","Art":"Lomre","Latin":"Microstomus kitt","Lengde":65.0,"Vekt":3000.0,"Norgesrekord":1800.0,"Link":"https:\/\/no.wikipedia.org\/wiki\/Lomre","Link_rekord":"https:\/\/www.klikk.no\/produkthjemmesider\/villmarksliv\/lomre-microstomus-kitt-3211916","Minimum_dyp":0.0,"Maximum_dyp":200.0},"Skrubbe":{"Familie":"Flyndrefamilien","Art":"Skrubbe","Latin":"Platichthys flesus","Lengde":60.0,"Vekt":4000.0,"Norgesrekord":2930.0,"Link":"https:\/\/no.wikipedia.org\/wiki\/Skrubbe","Link_rekord":"https:\/\/www.klikk.no\/produkthjemmesider\/villmarksliv\/skrubbe-platichthys-flesus-3222018","Minimum_dyp":0.0,"Maximum_dyp":100.0},"R\u00f8dspette":{"Familie":"Flyndrefamilien","Art":"R\u00f8dspette","Latin":"Pleuronectes platessa","Lengde":100.0,"Vekt":7000.0,"Norgesrekord":5200.0,"Link":"https:\/\/no.wikipedia.org\/wiki\/R%C3%B8dspette","Link_rekord":"https:\/\/www.klikk.no\/produkthjemmesider\/villmarksliv\/rodspette-pleuronectes-platessa-3238538","Minimum_dyp":10.0,"Maximum_dyp":200.0},"Bl\u00e5kveite":{"Familie":"Flyndrefamilien","Art":"Bl\u00e5kveite","Latin":"Reinhardtius hippoglossoides","Lengde":120.0,"Vekt":18000.0,"Norgesrekord":10800.0,"Link":"https:\/\/no.wikipedia.org\/wiki\/Bl%C3%A5kveite","Link_rekord":"https:\/\/www.klikk.no\/produkthjemmesider\/villmarksliv\/blakveite-reinhardtius-hippoglossoides-2930969","Minimum_dyp":200.0,"Maximum_dyp":2000.0},"Tunge":{"Familie":"Tungefamilien","Art":"Tunge","Latin":"Solea solea","Lengde":70.0,"Vekt":3000.0,"Norgesrekord":1980.0,"Link":"https:\/\/no.wikipedia.org\/wiki\/Tunge_(fisk)","Link_rekord":"https:\/\/www.hooked.no\/artikler\/denne-mannen-har-god-grunn-til-a-smile","Minimum_dyp":0.0,"Maximum_dyp":150.0},"Glasstunge":{"Familie":"Tungefamilien","Art":"Glasstunge","Latin":"Buglossidium luteum","Lengde":13.0,"Vekt":null,"Norgesrekord":3.4,"Link":"https:\/\/snl.no\/glasstunge","Link_rekord":"https:\/\/www.nrk.no\/rogaland\/fisk-pa-3_4-gram-vekkjer-oppsikt-1.12384198","Minimum_dyp":0.0,"Maximum_dyp":50.0},"Maisild":{"Familie":"Sildefamilien","Art":"Maisild","Latin":"Alosa alosa","Lengde":83.0,"Vekt":4000.0,"Norgesrekord":1256.0,"Link":"https:\/\/no.wikipedia.org\/wiki\/Maisild","Link_rekord":"https:\/\/www.klikk.no\/produkthjemmesider\/villmarksliv\/maisild-alosa-alosa-3212206","Minimum_dyp":null,"Maximum_dyp":null},"Stamsild":{"Familie":"Sildefamilien","Art":"Stamsild","Latin":"Alosa fallax","Lengde":60.0,"Vekt":1500.0,"Norgesrekord":758.0,"Link":"https:\/\/no.wikipedia.org\/wiki\/Stamsild","Link_rekord":"https:\/\/www.klikk.no\/produkthjemmesider\/villmarksliv\/stamsild-alosa-fallax-3222104","Minimum_dyp":null,"Maximum_dyp":null}}